pool_cue/__init__.py
pool_cue/config.py
pool_cue/context.py
pool_cue/exceptions.py
pool_cue/jobs.py
pool_cue/queue.py
pool_cue/serializers.py
pool_cue/threading.py
pool_cue/typing.py
pool_cue/utils.py
pool_cue/worker.py
pool_cue-1.3.0.dist-info/LICENSE
pool_cue-1.3.0.dist-info/METADATA
pool_cue-1.3.0.dist-info/WHEEL
pool_cue-1.3.0.dist-info/RECORD
