Metadata-Version: 2.1
Name: pool-cue
Version: 1.3.0
Summary: Tools for working with arq job queues
Home-page: https://github.com/skarre-r/pool-cue
Author: skarre-r
Author-email: skarre-r@protonmail.com
Requires-Python: >=3.11,<4.0
Classifier: Programming Language :: Python :: 3
Classifier: Programming Language :: Python :: 3.11
Requires-Dist: arq (>=0.25.0,<0.26.0)
Requires-Dist: msgpack (>=1.0.5,<2.0.0)
Requires-Dist: uvloop (>=0.17.0,<0.18.0)
Project-URL: Repository, https://github.com/skarre-r/pool-cue
